pyevt.cpython-38-darwin.so
libevt_python-20240421.dist-info/METADATA
libevt_python-20240421.dist-info/WHEEL
libevt_python-20240421.dist-info/top_level.txt
libevt_python-20240421.dist-info/RECORD
